smashrun/__init__.py
smashrun/client.py
smashrun_client-0.6.0.dist-info/METADATA
smashrun_client-0.6.0.dist-info/RECORD
smashrun_client-0.6.0.dist-info/WHEEL
smashrun_client-0.6.0.dist-info/top_level.txt
