Metadata-Version: 2.1
Name: smashrun-client
Version: 0.6.0
Summary: A Python client for the Smashrun API
Home-page: https://github.com/campbellr/smashrun-client
Author: Ryan Campbell
Author-email: campbellr@gmail.com
License: Apache
Keywords: smashrun
Platform: UNKNOWN
Classifier: Development Status :: 2 - Pre-Alpha
Classifier: Intended Audience :: Developers
Classifier: License :: OSI Approved :: Apache Software License
Classifier: Natural Language :: English
Classifier: Programming Language :: Python :: 2
Classifier: Programming Language :: Python :: 2.7
Classifier: Programming Language :: Python :: 3
Classifier: Programming Language :: Python :: 3.3
Classifier: Programming Language :: Python :: 3.4
Classifier: Programming Language :: Python :: 3.5
Requires-Dist: requests
Requires-Dist: requests-oauthlib
